oaf/__init__.py
oaf/bin/imgpkg
oaf-0.0.6.dist-info/LICENSE
oaf-0.0.6.dist-info/METADATA
oaf-0.0.6.dist-info/WHEEL
oaf-0.0.6.dist-info/top_level.txt
oaf-0.0.6.dist-info/RECORD
