Metadata-Version: 2.1
Name: oaf
Version: 0.0.6
Summary: Artifact storage using OCI registries
Home-page: https://github.com/old-ocean-creature/oaf
Maintainer: Sole Ahab
Project-URL: Documentation, https://github.com/old-ocean-creature/oaf
Project-URL: Code, https://github.com/old-ocean-creature/oaf
Project-URL: Issue tracker, https://github.com/old-ocean-creature/oaf
Requires-Python: >=3.6
License-File: LICENSE
